chroma_feedback/__init__.py
chroma_feedback/color.py
chroma_feedback/core.py
chroma_feedback/helper.py
chroma_feedback/install.py
chroma_feedback/logger.py
chroma_feedback/loop.py
chroma_feedback/metadata.py
chroma_feedback/reporter.py
chroma_feedback/request.py
chroma_feedback/ssdp.py
chroma_feedback/systray.py
chroma_feedback/types.py
chroma_feedback/wording.py
chroma_feedback/consumer/__init__.py
chroma_feedback/consumer/core.py
chroma_feedback/consumer/agile_innovative/blinkstick/__init__.py
chroma_feedback/consumer/agile_innovative/blinkstick/api.py
chroma_feedback/consumer/agile_innovative/blinkstick/core.py
chroma_feedback/consumer/agile_innovative/blinkstick/light.py
chroma_feedback/consumer/agile_innovative/blinkstick/types.py
chroma_feedback/consumer/compulab/fit_statusb/__init__.py
chroma_feedback/consumer/compulab/fit_statusb/api.py
chroma_feedback/consumer/compulab/fit_statusb/core.py
chroma_feedback/consumer/compulab/fit_statusb/light.py
chroma_feedback/consumer/compulab/fit_statusb/types.py
chroma_feedback/consumer/elgato/streamdeck/__init__.py
chroma_feedback/consumer/elgato/streamdeck/api.py
chroma_feedback/consumer/elgato/streamdeck/core.py
chroma_feedback/consumer/elgato/streamdeck/device.py
chroma_feedback/consumer/elgato/streamdeck/types.py
chroma_feedback/consumer/embrava/blynclight/__init__.py
chroma_feedback/consumer/embrava/blynclight/api.py
chroma_feedback/consumer/embrava/blynclight/core.py
chroma_feedback/consumer/embrava/blynclight/light.py
chroma_feedback/consumer/embrava/blynclight/types.py
chroma_feedback/consumer/embrava/blynclight_mini/__init__.py
chroma_feedback/consumer/embrava/blynclight_mini/api.py
chroma_feedback/consumer/embrava/blynclight_mini/core.py
chroma_feedback/consumer/embrava/blynclight_mini/light.py
chroma_feedback/consumer/embrava/blynclight_mini/types.py
chroma_feedback/consumer/embrava/blynclight_plus/__init__.py
chroma_feedback/consumer/embrava/blynclight_plus/api.py
chroma_feedback-13.5.1.dist-info/licenses/LICENSE.md
chroma_feedback-13.5.1.dist-info/METADATA
chroma_feedback-13.5.1.dist-info/WHEEL
chroma_feedback-13.5.1.dist-info/entry_points.txt
chroma_feedback-13.5.1.dist-info/top_level.txt
chroma_feedback-13.5.1.dist-info/RECORD
