Metadata-Version: 2.4
Name: chroma-feedback
Version: 13.5.1
Summary: Turn your RGB powered hardware into a status indicator for continuous integration, continuous deployment and infrastructure monitoring
Home-page: https://chroma-feedback.com
Author: Henry Ruhs
Author-email: info@henryruhs.com
License: MIT
Keywords: appveyor atlassian.bamboo atlassian.bitbucket betterstack buddy circle cloudbees.codeship custom datadog gitlab heroku jenkins jetbrains.teamcity microsoft.azure microsoft.github netlify travis uptimerobot vercel
License-File: LICENSE.md
Requires-Dist: busylight-for-humans==0.35.4
Requires-Dist: lifxlan==1.2.8
Requires-Dist: liquidctl==1.15.0
Requires-Dist: nanoleafapi==2.1.2
Requires-Dist: phue==1.1
Requires-Dist: python-magichue==0.3.2
Requires-Dist: pyqt6==6.9.1
Requires-Dist: pywizlight==0.6.2
Requires-Dist: requests==2.32.3
Requires-Dist: streamdeck==0.9.6
Requires-Dist: yeelight==0.7.16
Dynamic: author
Dynamic: author-email
Dynamic: description
Dynamic: description-content-type
Dynamic: home-page
Dynamic: keywords
Dynamic: license
Dynamic: license-file
Dynamic: requires-dist
Dynamic: summary
